Flask_SimpleAPI-0.7.0.dist-info/METADATA
Flask_SimpleAPI-0.7.0.dist-info/RECORD
Flask_SimpleAPI-0.7.0.dist-info/WHEEL
Flask_SimpleAPI-0.7.0.dist-info/entry_points.txt
Flask_SimpleAPI-0.7.0.dist-info/top_level.txt
flask_simpleapi/__init__.py
flask_simpleapi/cmd.py
flask_simpleapi/test_all.py
flask_simpleapi/wiki.py
flask_simpleapi/apis/__init__.py
flask_simpleapi/apis/session.py
flask_simpleapi/apis/user.py
flask_simpleapi/core/__init__.py
flask_simpleapi/core/decorators.py
flask_simpleapi/core/model.py
flask_simpleapi/core/response.py
flask_simpleapi/core/simple_api.py
flask_simpleapi/core/tools.py
flask_simpleapi/models/__init__.py
flask_simpleapi/models/base_perm.py
flask_simpleapi/models/base_session.py
flask_simpleapi/models/base_user.py
flask_simpleapi/project_template/__init__.py
flask_simpleapi/project_template/api.py
flask_simpleapi/project_template/settings.py
flask_simpleapi/project_template/apis/__init__.py
flask_simpleapi/project_template/apis/session.py
flask_simpleapi/project_template/apis/user.py
flask_simpleapi/project_template/models/__init__.py
flask_simpleapi/project_template/models/session.py
flask_simpleapi/project_template/models/user.py
flask_simpleapi/tests/__init__.py
flask_simpleapi/tests/app.py
flask_simpleapi/tests/user.py
tests/__init__.py
tests/test_simpleapi.py
tests/user.py
