Metadata-Version: 2.1
Name: Flask-SimpleAPI
Version: 0.7.0
Summary: Very simple way to create an API with Flask
Home-page: http://bkinno.pro
Author: Bkinno
Author-email: tronghieu.ha@gmail.com
License: MIT
Platform: any
Classifier: Environment :: Web Environment
Classifier: Intended Audience :: Developers
Classifier: License :: OSI Approved :: BSD License
Classifier: Operating System :: OS Independent
Classifier: Programming Language :: Python
Classifier: Topic :: Internet :: WWW/HTTP :: Dynamic Content
Classifier: Topic :: Software Development :: Libraries :: Python Modules
Requires-Dist: flask
Requires-Dist: mongoengine
